words2nums/__init__.py
words2nums/core/__init__.py
words2nums/core/converter.py
words2nums/core/evaluator.py
words2nums/core/exceptions.py
words2nums/core/handler.py
words2nums/core/parser.py
words2nums/core/tokenizer.py
words2nums/core/types.py
words2nums/locales/__init__.py
words2nums/locales/english/__init__.py
words2nums/locales/english/evaluator.py
words2nums/locales/english/exceptions.py
words2nums/locales/english/handler.py
words2nums/locales/english/parser.py
words2nums/locales/english/tokenizer.py
words2nums/locales/english/tree.py
words2nums-0.1.2.dist-info/LICENSE
words2nums-0.1.2.dist-info/METADATA
words2nums-0.1.2.dist-info/WHEEL
words2nums-0.1.2.dist-info/top_level.txt
words2nums-0.1.2.dist-info/RECORD
