Metadata-Version: 2.1
Name: words2nums
Version: 0.1.2
Summary: Lightweight words to number converter with several locales support
Author-email: Andrew Hrimov <andrew.hrimov@gmail.com>
License: Apache-2.0
Project-URL: Source, https://github.com/hrimov/words2nums
Project-URL: Homepage, https://github.com/hrimov/words2nums
Project-URL: Documentation, https://words2nums.readthedocs.io
Project-URL: Bug Tracker, https://github.com/hrimov/words2nums/issues
Classifier: Programming Language :: Python :: 3.11
Classifier: Programming Language :: Python :: 3.12
Classifier: Programming Language :: Python :: 3.13
Classifier: Operating System :: OS Independent
Requires-Python: >=3.11
License-File: LICENSE
Provides-Extra: docs
Requires-Dist: sphinx; extra == "docs"
Requires-Dist: sphinx-rtd-theme; extra == "docs"
Requires-Dist: sphinx-autodocgen==1.3; extra == "docs"
Requires-Dist: furo==2024.8.*; extra == "docs"
Provides-Extra: lint
Requires-Dist: ruff==0.8.4; extra == "lint"
Requires-Dist: mypy==1.13.0; extra == "lint"
Provides-Extra: test
Requires-Dist: pytest==8.3.0; extra == "test"
Requires-Dist: pytest-cov==6.0.0; extra == "test"
Requires-Dist: coverage-badge==1.1.2; extra == "test"
